symbolic/__init__.py
symbolic/libVAL.dylib
symbolic/libsymbolic.dylib
symbolic/problem.py
symbolic/pysymbolic.cpython-39-darwin.so
symbolic/include/symbolic/action.h
symbolic/include/symbolic/axiom.h
symbolic/include/symbolic/derived_predicate.h
symbolic/include/symbolic/formula.h
symbolic/include/symbolic/normal_form.h
symbolic/include/symbolic/object.h
symbolic/include/symbolic/pddl.h
symbolic/include/symbolic/predicate.h
symbolic/include/symbolic/proposition.h
symbolic/include/symbolic/state.h
symbolic/include/symbolic/symbolic
symbolic/include/symbolic/planning/a_star.h
symbolic/include/symbolic/planning/breadth_first_search.h
symbolic/include/symbolic/planning/depth_first_search.h
symbolic/include/symbolic/planning/planner.h
symbolic/include/symbolic/utils/combination_generator.h
symbolic/include/symbolic/utils/hash_set.h
symbolic/include/symbolic/utils/parameter_generator.h
symbolic/include/symbolic/utils/unique_vector.h
symbolic/lib/cmake/symbolic/symbolicConfig.cmake
symbolic/lib/cmake/symbolic/symbolicConfigVersion.cmake
symbolic/lib/cmake/symbolic/symbolicTargets-release.cmake
symbolic/lib/cmake/symbolic/symbolicTargets.cmake
pysymbolic-1.0.2.dist-info/LICENSE
pysymbolic-1.0.2.dist-info/METADATA
pysymbolic-1.0.2.dist-info/WHEEL
pysymbolic-1.0.2.dist-info/top_level.txt
pysymbolic-1.0.2.dist-info/RECORD
