Metadata-Version: 2.1
Name: pysymbolic
Version: 1.0.2
Summary: PDDL symbolic library
Author-email: Toki Migimatsu <takatoki@cs.stanford.edu>
License: MIT License        
Project-URL: Homepage, https://github.com/tmigimatsu/symbolic
Classifier: Programming Language :: Python :: 3
Classifier: License :: OSI Approved :: MIT License
Classifier: Operating System :: OS Independent
Requires-Python: >=3.7
License-File: LICENSE
